dagster_wandb/__init__.py
dagster_wandb/io_manager.py
dagster_wandb/py.typed
dagster_wandb/resources.py
dagster_wandb/types.py
dagster_wandb/version.py
dagster_wandb/launch/__init__.py
dagster_wandb/launch/configs.py
dagster_wandb/launch/ops.py
dagster_wandb/utils/__init__.py
dagster_wandb/utils/errors.py
dagster_wandb/utils/pickling.py
dagster_wandb-0.28.13.dist-info/licenses/LICENSE
dagster_wandb-0.28.13.dist-info/METADATA
dagster_wandb-0.28.13.dist-info/WHEEL
dagster_wandb-0.28.13.dist-info/top_level.txt
dagster_wandb-0.28.13.dist-info/RECORD
