Metadata-Version: 2.4
Name: dagster-wandb
Version: 0.28.13
Summary: Package for wandb Dagster components.
Home-page: https://github.com/dagster-io/dagster/tree/master/python_modules/libraries/dagster-wandb
Author: Dagster Labs
Author-email: hello@dagsterlabs.com
License: Apache-2.0
Classifier: Programming Language :: Python :: 3.10
Classifier: Programming Language :: Python :: 3.11
Classifier: License :: OSI Approved :: Apache Software License
Classifier: Operating System :: OS Independent
Requires-Python: >=3.10,<3.15
License-File: LICENSE
Requires-Dist: dagster==1.12.13
Requires-Dist: wandb<1.0,>=0.15.11
Provides-Extra: dev
Requires-Dist: cloudpickle; extra == "dev"
Requires-Dist: joblib; extra == "dev"
Requires-Dist: callee; extra == "dev"
Requires-Dist: dill; extra == "dev"
Dynamic: author
Dynamic: author-email
Dynamic: classifier
Dynamic: home-page
Dynamic: license
Dynamic: license-file
Dynamic: provides-extra
Dynamic: requires-dist
Dynamic: requires-python
Dynamic: summary
